rtl/shift_register/bidirectional.v
module bidirectional_shift #(
    parameter N = 8
)(
    input  wire clk,
    input  wire rst,
    input  wire load,
    input  wire shift_en,
    input  wire dir,               // 0: left, 1: right
    input  wire serial_in_left,
    input  wire serial_in_right,
    input  wire [N-1:0] parallel_in,
    output reg  [N-1:0] data_out
);

always @(posedge clk or negedge rst) begin
    if (!rst)
        data_out <= 0;
    else if (load)
        data_out <= parallel_in;
    else if (shift_en) begin
        if (dir == 1'b0)
            data_out <= {data_out[N-2:0], serial_in_left};   // shift left
        else
            data_out <= {serial_in_right, data_out[N-1:1]};  // shift right
    end
end

endmodule

tb/bidirectional_tb.v
`timescale 1ns / 1ps

module bidirectional_tb;

    // Parameters
    localparam N = 8;

    // DUT signals
    reg             clk;
    reg             rst;
    reg             load;
    reg             shift_en;
    reg             dir;             // 0 = shift left, 1 = shift right
    reg             serial_in_left;
    reg             serial_in_right;
    reg  [N-1:0]    parallel_in;
    wire [N-1:0]    data_out;

    // DUT instantiation
    bidirectional_shift #(.N(N)) dut (
        .clk            (clk),
        .rst            (rst),
        .load           (load),
        .shift_en       (shift_en),
        .dir            (dir),
        .serial_in_left (serial_in_left),
        .serial_in_right(serial_in_right),
        .parallel_in    (parallel_in),
        .data_out       (data_out)
    );

    // Clock: 10 ns period
    initial clk = 0;
    always #5 clk = ~clk;

    // Task: wait n rising edges
    task tick;
        input integer n;
        repeat (n) @(posedge clk);
    endtask

    // Task: parallel load for 1 cycle then deassert
    task do_load;
        input [N-1:0] data;
        begin
            parallel_in = data;
            load = 1;
            tick(1);
            load = 0;
        end
    endtask

    // Stimulus
    initial begin
        $dumpfile("bidirectional.vcd");
        $dumpvars(0, bidirectional_tb);

        // Initialise
        rst = 0; load = 0; shift_en = 0;
        dir = 0; serial_in_left = 0; serial_in_right = 0;
        parallel_in = {N{1'b0}};

        // Reset: hold for 2 cycles then release
        tick(2);
        rst = 1;

        // ----------------------------------------------------------------
        // Parallel load
        // ----------------------------------------------------------------
        do_load(8'hA5);
        $display("After load       : data_out = %b  (exp 10100101)", data_out);

        // ----------------------------------------------------------------
        // Shift left x4, serial_in_left = 0
        // ----------------------------------------------------------------
        dir = 0; serial_in_left = 0; shift_en = 1;
        repeat (4) begin
            tick(1);
            $display("Shift left       : data_out = %b", data_out);
        end
        shift_en = 0;

        // ----------------------------------------------------------------
        // Reload and shift right x4, serial_in_right = 1
        // ----------------------------------------------------------------
        do_load(8'hA5);
        $display("After reload     : data_out = %b  (exp 10100101)", data_out);

        dir = 1; serial_in_right = 1; shift_en = 1;
        repeat (4) begin
            tick(1);
            $display("Shift right      : data_out = %b", data_out);
        end
        shift_en = 0;

        // ----------------------------------------------------------------
        // Hold: shift_en = 0, data_out must stay unchanged
        // ----------------------------------------------------------------
        tick(2);
        $display("Hold             : data_out = %b  (unchanged)", data_out);

        // ----------------------------------------------------------------
        // Async reset mid-cycle
        // ----------------------------------------------------------------
        shift_en = 1; dir = 0;
        #3;
        rst = 0;
        #2;
        $display("Async reset      : data_out = %b  (exp 00000000)", data_out);
        rst = 1; shift_en = 0;

        tick(2);
        $display("Simulation done.");
        $finish;
    end

endmodule

sim/bidirectional.vcd
$date
	Tue Mar  3 00:08:42 2026
$end
$version
	ModelSim Version 2020.1
$end
$timescale
	1ps
$end

$scope module bidirectional_tb $end
$var parameter 32 ! N $end
$var reg 1 " clk $end
$var reg 1 # rst $end
$var reg 1 $ load $end
$var reg 1 % shift_en $end
$var reg 1 & dir $end
$var reg 1 ' serial_in_left $end
$var reg 1 ( serial_in_right $end
$var reg 8 ) parallel_in [7:0] $end
$var wire 1 * data_out [7] $end
$var wire 1 + data_out [6] $end
$var wire 1 , data_out [5] $end
$var wire 1 - data_out [4] $end
$var wire 1 . data_out [3] $end
$var wire 1 / data_out [2] $end
$var wire 1 0 data_out [1] $end
$var wire 1 1 data_out [0] $end

$scope module dut $end
$var parameter 32 2 N $end
$var wire 1 3 clk $end
$var wire 1 4 rst $end
$var wire 1 5 load $end
$var wire 1 6 shift_en $end
$var wire 1 7 dir $end
$var wire 1 8 serial_in_left $end
$var wire 1 9 serial_in_right $end
$var wire 1 : parallel_in [7] $end
$var wire 1 ; parallel_in [6] $end
$var wire 1 < parallel_in [5] $end
$var wire 1 = parallel_in [4] $end
$var wire 1 > parallel_in [3] $end
$var wire 1 ? parallel_in [2] $end
$var wire 1 @ parallel_in [1] $end
$var wire 1 A parallel_in [0] $end
$var reg 8 B data_out [7:0] $end
$upscope $end
$upscope $end
$enddefinitions $end
#0
$dumpvars
0"
0#
0$
0%
0&
0'
0(
b0 )
b0 B
b1000 !
b1000 2
01
00
0/
0.
0-
0,
0+
0*
0A
0@
0?
0>
0=
0<
0;
0:
09
08
07
06
05
04
03
$end
#5000
1"
13
#10000
0"
03
#15000
1"
13
1#
14
#20000
0"
03
#25000
1"
13
b10100101 )
1$
1A
1?
1<
1:
15
#30000
0"
03
#35000
1"
13
0$
1%
05
16
b10100101 B
11
1/
1,
1*
#40000
0"
03
#45000
1"
13
b1001010 B
01
10
0/
1.
0,
1+
0*
#50000
0"
03
#55000
1"
13
b10010100 B
00
1/
0.
1-
0+
1*
#60000
0"
03
#65000
1"
13
0%
1$
06
15
b101000 B
0/
1.
0-
1,
0*
#70000
0"
03
#75000
1"
13
0$
1&
1%
05
17
16
b10100101 B
11
1/
0.
1*
#80000
0"
03
#85000
1"
13
b1010010 B
01
10
0/
1-
0,
1+
0*
#90000
0"
03
#95000
1"
13
b101001 B
11
00
1.
0-
1,
0+
#100000
0"
03
#105000
1"
13
0%
06
b10100 B
01
1/
0.
1-
0,
#110000
0"
03
#115000
1"
13
0#
04
b0 B
0/
0-
#118000
1#
14
