rtl/shift_register/bidirectional.v
module bidirectional_shift #(
    parameter N = 8
)(
    input  wire clk,
    input  wire rst,
    input  wire load,
    input  wire shift_en,
    input  wire dir,               // 0: left, 1: right
    input  wire serial_in_left,
    input  wire serial_in_right,
    input  wire [N-1:0] parallel_in,
    output reg  [N-1:0] data_out
);

always @(posedge clk or negedge rst) begin
    if (!rst)
        data_out <= 0;
    else if (load)
        data_out <= parallel_in;
    else if (shift_en) begin
        if (dir == 1'b0)
            data_out <= {data_out[N-2:0], serial_in_left};   // shift left
        else
            data_out <= {serial_in_right, data_out[N-1:1]};  // shift right
    end
end

endmodule

tb/bidirectional_tb.v
`timescale 1ns / 1ps

module bidirectional_tb;

    // Parameters
    localparam N = 8;

    // DUT signals
    reg             clk;
    reg             rst;
    reg             load;
    reg             shift_en;
    reg             dir;             // 0 = shift left, 1 = shift right
    reg             serial_in_left;
    reg             serial_in_right;
    reg  [N-1:0]    parallel_in;
    wire [N-1:0]    data_out;

    // DUT instantiation
    bidirectional_shift #(.N(N)) dut (
        .clk            (clk),
        .rst            (rst),
        .load           (load),
        .shift_en       (shift_en),
        .dir            (dir),
        .serial_in_left (serial_in_left),
        .serial_in_right(serial_in_right),
        .parallel_in    (parallel_in),
        .data_out       (data_out)
    );

    // Clock: 10 ns period
    initial clk = 0;
    always #5 clk = ~clk;

    // Task: wait n rising edges
    task tick;
        input integer n;
        repeat (n) @(posedge clk);
    endtask

    // Task: parallel load for 1 cycle then deassert
    task do_load;
        input [N-1:0] data;
        begin
            parallel_in = data;
            load = 1;
            tick(1);
            load = 0;
        end
    endtask

    // Stimulus
    initial begin
        $dumpfile("bidirectional.vcd");
        $dumpvars(0, bidirectional_tb);

        // Initialise
        rst = 0; load = 0; shift_en = 0;
        dir = 0; serial_in_left = 0; serial_in_right = 0;
        parallel_in = {N{1'b0}};

        // Reset: hold for 2 cycles then release
        tick(2);
        rst = 1;

        // ----------------------------------------------------------------
        // Parallel load
        // ----------------------------------------------------------------
        do_load(8'hA5);
        $display("After load       : data_out = %b  (exp 10100101)", data_out);

        // ----------------------------------------------------------------
        // Shift left x4, serial_in_left = 0
        // ----------------------------------------------------------------
        dir = 0; serial_in_left = 0; shift_en = 1;
        repeat (4) begin
            tick(1);
            $display("Shift left       : data_out = %b", data_out);
        end
        shift_en = 0;

        // ----------------------------------------------------------------
        // Reload and shift right x4, serial_in_right = 1
        // ----------------------------------------------------------------
        do_load(8'hA5);
        $display("After reload     : data_out = %b  (exp 10100101)", data_out);

        dir = 1; serial_in_right = 1; shift_en = 1;
        repeat (4) begin
            tick(1);
            $display("Shift right      : data_out = %b", data_out);
        end
        shift_en = 0;

        // ----------------------------------------------------------------
        // Hold: shift_en = 0, data_out must stay unchanged
        // ----------------------------------------------------------------
        tick(2);
        $display("Hold             : data_out = %b  (unchanged)", data_out);

        // ----------------------------------------------------------------
        // Async reset mid-cycle
        // ----------------------------------------------------------------
        shift_en = 1; dir = 0;
        #3;
        rst = 0;
        #2;
        $display("Async reset      : data_out = %b  (exp 00000000)", data_out);
        rst = 1; shift_en = 0;

        tick(2);
        $display("Simulation done.");
        $finish;
    end

endmodule

sim/bidirectional.vcd
$date
	Tue Mar  3 18:19:46 2026
$end
$version
	ModelSim Version 2020.1
$end
$timescale
	1ps
$end

$scope module bidirectional_tb $end
$var parameter 32 ! N $end
$var reg 1 " clk $end
$var reg 1 # rst $end
$var reg 1 $ load $end
$var reg 1 % shift_en $end
$var reg 1 & dir $end
$var reg 1 ' serial_in_left $end
$var reg 1 ( serial_in_right $end
$var reg 8 ) parallel_in [7:0] $end
$var wire 1 * data_out [7] $end
$var wire 1 + data_out [6] $end
$var wire 1 , data_out [5] $end
$var wire 1 - data_out [4] $end
$var wire 1 . data_out [3] $end
$var wire 1 / data_out [2] $end
$var wire 1 0 data_out [1] $end
$var wire 1 1 data_out [0] $end

$scope task tick $end
$var integer 32 2 n $end
$upscope $end

$scope task do_load $end
$var reg 8 3 data [7:0] $end
$upscope $end

$scope module dut $end
$var parameter 32 4 N $end
$var wire 1 5 clk $end
$var wire 1 6 rst $end
$var wire 1 7 load $end
$var wire 1 8 shift_en $end
$var wire 1 9 dir $end
$var wire 1 : serial_in_left $end
$var wire 1 ; serial_in_right $end
$var wire 1 < parallel_in [7] $end
$var wire 1 = parallel_in [6] $end
$var wire 1 > parallel_in [5] $end
$var wire 1 ? parallel_in [4] $end
$var wire 1 @ parallel_in [3] $end
$var wire 1 A parallel_in [2] $end
$var wire 1 B parallel_in [1] $end
$var wire 1 C parallel_in [0] $end
$var reg 8 D data_out [7:0] $end
$upscope $end
$upscope $end
$enddefinitions $end
#0
$dumpvars
0"
0#
0$
0%
0&
0'
0(
b0 )
b0 D
bx 3
b1000 !
b1000 4
b10 2
01
00
0/
0.
0-
0,
0+
0*
0C
0B
0A
0@
0?
0>
0=
0<
0;
0:
09
08
07
06
05
$end
#5000
1"
15
#10000
0"
05
#15000
1"
15
1#
b10100101 3
b10100101 )
1$
b1 2
1C
1A
1>
1<
17
16
#20000
0"
05
#25000
1"
15
0$
1%
07
18
b10100101 D
11
1/
1,
1*
#30000
0"
05
#35000
1"
15
b1001010 D
01
10
0/
1.
0,
1+
0*
#40000
0"
05
#45000
1"
15
b10010100 D
00
1/
0.
1-
0+
1*
#50000
0"
05
#55000
1"
15
b101000 D
0/
1.
0-
1,
0*
#60000
0"
05
#65000
1"
15
0%
1$
08
17
b1010000 D
0.
1-
0,
1+
#70000
0"
05
#75000
1"
15
0$
1&
1(
1%
07
19
1;
18
b10100101 D
11
1/
0-
1,
0+
1*
#80000
0"
05
#85000
1"
15
b11010010 D
01
10
0/
1-
0,
1+
#90000
0"
05
#95000
1"
15
b11101001 D
11
00
1.
0-
1,
#100000
0"
05
#105000
1"
15
b11110100 D
01
1/
0.
1-
#110000
0"
05
#115000
1"
15
0%
b10 2
08
b11111010 D
10
0/
1.
#120000
0"
05
#125000
1"
15
#130000
0"
05
#135000
1"
15
1%
0&
18
09
#138000
0#
06
b0 D
00
0.
0-
0,
0+
0*
#140000
0"
1#
0%
08
05
16
