rtl/counter/johnson_counter.v
module johnson_counter #(
    parameter integer N     = 16,
)(
    input  wire             clk,
    input  wire             rst,
    output reg  [N-1:0] out
);
always @(posedge clk or negedge rst) begin
    if (!rst)
        out <= '0;
    else
        out <= {out[N-2:0], ~out[N-1]};
end
endmodule

tb/johnson_counter_tb.v
`timescale 1ns/1ps

module johnson_counter_tb;

    parameter N = 4;

    reg clk;
    reg rst;
    wire [N-1:0] out;

    // Instantiate DUT
    johnson_counter #(
        .N(N)
    ) dut (
        .clk(clk),
        .rst(rst),
        .out(out)
    );

    // Clock generation (10ns period)
    initial begin
        clk = 0;
        forever #5 clk = ~clk;
    end

    // Stimulus
    initial begin
        $display("Starting Johnson Counter Test...");
        $monitor("Time=%0t | rst=%b | out=%b", $time, rst, out);

        rst = 0;
        #12;          // hold reset
        rst = 1;      // release reset

        // run 2N period
        #(2*N*10);

        $display("Test finished.");
        $finish;
    end

    // Dump waveform (ModelSim/VCD)
    initial begin
        $dumpfile("johnson_counter.vcd");
        $dumpvars(0, johnson_counter_tb);
    end

endmodule

sim/johnson_counter.vcd
$date
	Tue Mar  3 21:27:56 2026
$end
$version
	ModelSim Version 2020.1
$end
$timescale
	1ps
$end

$scope module johnson_counter_tb $end
$var parameter 32 ! N $end
$var reg 1 " clk $end
$var reg 1 # rst $end
$var wire 1 $ out [3] $end
$var wire 1 % out [2] $end
$var wire 1 & out [1] $end
$var wire 1 ' out [0] $end

$scope module dut $end
$var parameter 32 ( N $end
$var wire 1 ) clk $end
$var wire 1 * rst $end
$var reg 4 + out [3:0] $end
$upscope $end
$upscope $end
$enddefinitions $end
#0
$dumpvars
0"
0#
b0 +
b100 !
b100 (
0'
0&
0%
0$
0*
0)
$end
#5000
1"
1)
#10000
0"
0)
#12000
1#
1*
#15000
1"
1)
b1 +
1'
#20000
0"
0)
#25000
1"
1)
b11 +
1&
#30000
0"
0)
#35000
1"
1)
b111 +
1%
#40000
0"
0)
#45000
1"
1)
b1111 +
1$
#50000
0"
0)
#55000
1"
1)
b1110 +
0'
#60000
0"
0)
#65000
1"
1)
b1100 +
0&
#70000
0"
0)
#75000
1"
1)
b1000 +
0%
#80000
0"
0)
#85000
1"
1)
b0 +
0$
