rtl/adder/full_adder.v
// -----------------------------------------------------------------------------
// File    : full_adder.v
// Module  : full_adder
// Brief   : 1-bit full adder. Computes Sum = A ^ B ^ Cin and
//           Carry = (A & B) | (Cin & (A ^ B)).
// Rev     : 1.0  2026-03-02  Initial release
// -----------------------------------------------------------------------------
module full_adder(
    input  wire A,
    input  wire B,
    input  wire Cin,
    output wire Sum,
    output wire Carry
    );
    assign Sum = A ^ B ^ Cin;
    assign Carry = (A & B) | (Cin & (A ^ B));
endmodule

rtl/adder/full_adder_4bit.v
module full_adder_4bit (
  input wire [3:0] a,
  input wire [3:0] b,
  input wire carry_in,
  output wire [3:0] sum,
  output wire carry_out
);

  wire c1, c2, c3;

  full_adder fa0 (
    .A(a[0]),
    .B(b[0]),
    .Cin(carry_in),
    .Sum(sum[0]),
    .Carry(c1)
  );

  full_adder fa1 (
    .A(a[1]),
    .B(b[1]),
    .Cin(c1),
    .Sum(sum[1]),
    .Carry(c2)
  );

  full_adder fa2 (
    .A(a[2]),
    .B(b[2]),
    .Cin(c2),
    .Sum(sum[2]),
    .Carry(c3)
  );

  full_adder fa3 (
    .A(a[3]),
    .B(b[3]),
    .Cin(c3),
    .Sum(sum[3]),
    .Carry(carry_out)
  );

endmodule

tb/full_adder_4bit_tb.v
`timescale 1ns/1ps

module full_adder_4bit_tb;

reg  [3:0] a_tb, b_tb;
reg        cin_tb;
wire [3:0] sum_tb;
wire       carry_tb;

integer i,j,k;
integer errors = 0;
reg [4:0] expected;

full_adder_4bit dut (
  .a(a_tb),
  .b(b_tb),
  .carry_in(cin_tb),
  .sum(sum_tb),
  .carry_out(carry_tb)
);

initial begin
  $dumpfile("wave.vcd");
  $dumpvars(0, full_adder_4bit_tb);

  for (i=0;i<16;i=i+1)
    for (j=0;j<16;j=j+1)
      for (k=0;k<2;k=k+1) begin
        a_tb = i;
        b_tb = j;
        cin_tb = k;
        #1;
        expected = i + j + k;

        if ({carry_tb,sum_tb} !== expected) begin
          errors = errors + 1;
          $display("ERROR: %d + %d + %d", i,j,k);
        end

        #9;
      end

  $display("Simulation done. Errors = %0d", errors);
  $finish;
end

endmodule

sim/wave.vcd
$date
	Tue Feb 24 16:43:34 2026
$end
$version
	ModelSim Version 2020.1
$end
$timescale
	1ps
$end

$scope module full_adder_4bit_tb $end
$var reg 4 ! a_tb [3:0] $end
$var reg 4 " b_tb [3:0] $end
$var reg 1 # cin_tb $end
$var wire 1 $ sum_tb [3] $end
$var wire 1 % sum_tb [2] $end
$var wire 1 & sum_tb [1] $end
$var wire 1 ' sum_tb [0] $end
$var wire 1 ( carry_tb $end
$var integer 32 ) i $end
$var integer 32 * j $end
$var integer 32 + k $end
$var integer 32 , errors $end
$var reg 5 - expected [4:0] $end

$scope module dut $end
$var wire 1 . a [3] $end
$var wire 1 / a [2] $end
$var wire 1 0 a [1] $end
$var wire 1 1 a [0] $end
$var wire 1 2 b [3] $end
$var wire 1 3 b [2] $end
$var wire 1 4 b [1] $end
$var wire 1 5 b [0] $end
$var wire 1 6 carry_in $end
$var wire 1 $ sum [3] $end
$var wire 1 % sum [2] $end
$var wire 1 & sum [1] $end
$var wire 1 ' sum [0] $end
$var wire 1 ( carry_out $end
$var wire 1 7 c1 $end
$var wire 1 8 c2 $end
$var wire 1 9 c3 $end

$scope module fa0 $end
$var wire 1 1 A $end
$var wire 1 5 B $end
$var wire 1 6 Cin $end
$var wire 1 ' Sum $end
$var wire 1 7 Carry $end
$upscope $end

$scope module fa1 $end
$var wire 1 0 A $end
$var wire 1 4 B $end
$var wire 1 7 Cin $end
$var wire 1 & Sum $end
$var wire 1 8 Carry $end
$upscope $end

$scope module fa2 $end
$var wire 1 / A $end
$var wire 1 3 B $end
$var wire 1 8 Cin $end
$var wire 1 % Sum $end
$var wire 1 9 Carry $end
$upscope $end

$scope module fa3 $end
$var wire 1 . A $end
$var wire 1 2 B $end
$var wire 1 9 Cin $end
$var wire 1 $ Sum $end
$var wire 1 ( Carry $end
$upscope $end
$upscope $end
$upscope $end
$enddefinitions $end
#0
$dumpvars
b0 !
b0 "
0#
bx -
b0 )
b0 *
b0 +
b0 ,
0'
0&
0%
0$
0(
07
08
09
06
05
04
03
02
01
00
0/
0.
$end
#1000
b0 -
#10000
b1 +
1#
16
1'
#11000
b1 -
#20000
b10 +
b1 *
b0 +
b1 "
0#
15
06
#30000
b1 +
1#
16
0'
17
1&
#31000
b10 -
#40000
b10 +
b10 *
b0 +
b10 "
0#
05
14
06
0&
18
07
1&
08
#50000
b1 +
1#
16
1'
#51000
b11 -
#60000
b10 +
b11 *
b0 +
b11 "
0#
15
06
#70000
b1 +
1#
16
0'
17
0&
18
1%
#71000
b100 -
#80000
b10 +
b100 *
b0 +
b100 "
0#
05
04
13
06
0%
19
1&
08
07
0&
1%
09
#90000
b1 +
1#
16
1'
#91000
b101 -
#100000
b10 +
b101 *
b0 +
b101 "
0#
15
06
#110000
b1 +
1#
16
0'
17
1&
#111000
b110 -
#120000
b10 +
b110 *
b0 +
b110 "
0#
05
14
06
0&
18
07
1&
08
#130000
b1 +
1#
16
1'
#131000
b111 -
#140000
b10 +
b111 *
b0 +
b111 "
0#
15
06
#150000
b1 +
1#
16
0'
17
0&
18
0%
19
1$
#151000
b1000 -
#160000
b10 +
b1000 *
b0 +
b1000 "
0#
05
04
03
12
06
0$
1(
1%
09
1&
08
07
0&
0%
1$
0(
#170000
b1 +
1#
16
1'
#171000
b1001 -
#180000
b10 +
b1001 *
b0 +
b1001 "
0#
15
06
#190000
b1 +
1#
16
0'
17
1&
#191000
b1010 -
#200000
b10 +
b1010 *
b0 +
b1010 "
0#
05
14
06
0&
18
07
1&
08
#210000
b1 +
1#
16
1'
#211000
b1011 -
#220000
b10 +
b1011 *
b0 +
b1011 "
0#
15
06
#230000
b1 +
1#
16
0'
17
0&
18
1%
#231000
b1100 -
#240000
b10 +
b1100 *
b0 +
b1100 "
0#
05
04
13
06
0%
19
1&
08
07
0&
1%
09
#250000
b1 +
1#
16
1'
#251000
b1101 -
#260000
b10 +
b1101 *
b0 +
b1101 "
0#
15
06
#270000
b1 +
1#
16
0'
17
1&
#271000
b1110 -
#280000
b10 +
b1110 *
b0 +
b1110 "
0#
05
14
06
0&
18
07
1&
08
#290000
b1 +
1#
16
1'
#291000
b1111 -
#300000
b10 +
b1111 *
b0 +
b1111 "
0#
15
06
#310000
b1 +
1#
16
0'
17
0&
18
0%
19
0$
1(
#311000
b10000 -
#320000
b10 +
b10000 *
b1 )
b0 *
b0 +
b1 !
b0 "
0#
05
04
03
02
11
06
1$
0(
1%
09
1&
08
1'
07
0&
0%
0$
#321000
b1 -
#330000
b1 +
1#
16
0'
17
1&
#331000
b10 -
#340000
b10 +
b1 *
b0 +
b1 "
0#
15
06
#350000
b1 +
1#
16
1'
#351000
b11 -
#360000
b10 +
b10 *
b0 +
b10 "
0#
05
14
06
07
#370000
b1 +
1#
16
0'
17
0&
18
1%
#371000
b100 -
#380000
b10 +
b11 *
b0 +
b11 "
0#
15
06
#390000
b1 +
1#
16
1'
#391000
b101 -
#400000
b10 +
b100 *
b0 +
b100 "
0#
05
04
13
06
07
0%
19
08
1%
09
#410000
b1 +
1#
16
0'
17
1&
#411000
b110 -
#420000
b10 +
b101 *
b0 +
b101 "
0#
15
06
#430000
b1 +
1#
16
1'
#431000
b111 -
#440000
b10 +
b110 *
b0 +
b110 "
0#
05
14
06
07
#450000
b1 +
1#
16
0'
17
0&
18
0%
19
1$
#451000
b1000 -
#460000
b10 +
b111 *
b0 +
b111 "
0#
15
06
#470000
b1 +
1#
16
1'
#471000
b1001 -
#480000
b10 +
b1000 *
b0 +
b1000 "
0#
05
04
03
12
06
07
0$
1(
1%
09
08
0%
1$
0(
#490000
b1 +
1#
16
0'
17
1&
#491000
b1010 -
#500000
b10 +
b1001 *
b0 +
b1001 "
0#
15
06
#510000
b1 +
1#
16
1'
#511000
b1011 -
#520000
b10 +
b1010 *
b0 +
b1010 "
0#
05
14
06
07
#530000
b1 +
1#
16
0'
17
0&
18
1%
#531000
b1100 -
#540000
b10 +
b1011 *
b0 +
b1011 "
0#
15
06
#550000
b1 +
1#
16
1'
#551000
b1101 -
#560000
b10 +
b1100 *
b0 +
b1100 "
0#
05
04
13
06
07
0%
19
08
1%
09
#570000
b1 +
1#
16
0'
17
1&
#571000
b1110 -
#580000
b10 +
b1101 *
b0 +
b1101 "
0#
15
06
#590000
b1 +
1#
16
1'
#591000
b1111 -
#600000
b10 +
b1110 *
b0 +
b1110 "
0#
05
14
06
07
#610000
b1 +
1#
16
0'
17
0&
18
0%
19
0$
1(
#611000
b10000 -
#620000
b10 +
b1111 *
b0 +
b1111 "
0#
15
06
#630000
b1 +
1#
16
1'
#631000
b10001 -
#640000
b10 +
b10000 *
b10 )
b0 *
b0 +
b10 !
b0 "
0#
05
04
03
02
01
10
06
07
1$
0(
1%
09
1&
08
0'
0%
0$
#641000
b10 -
#650000
b1 +
1#
16
1'
#651000
b11 -
#660000
b10 +
b1 *
b0 +
b1 "
0#
15
06
#670000
b1 +
1#
16
0'
17
0&
18
1%
#671000
b100 -
#680000
b10 +
b10 *
b0 +
b10 "
0#
05
14
06
1&
07
0&
#690000
b1 +
1#
16
1'
#691000
b101 -
#700000
b10 +
b11 *
b0 +
b11 "
0#
15
06
#710000
b1 +
1#
16
0'
17
1&
#711000
b110 -
#720000
b10 +
b100 *
b0 +
b100 "
0#
05
04
13
06
0%
19
0&
07
1&
08
1$
1%
09
0$
#730000
b1 +
1#
16
1'
#731000
b111 -
#740000
b10 +
b101 *
b0 +
b101 "
0#
15
06
#750000
b1 +
1#
16
0'
17
0&
18
0%
19
1$
#751000
b1000 -
#760000
b10 +
b110 *
b0 +
b110 "
0#
05
14
06
1&
07
0&
#770000
b1 +
1#
16
1'
#771000
b1001 -
#780000
b10 +
b111 *
b0 +
b111 "
0#
15
06
#790000
b1 +
1#
16
0'
17
1&
#791000
b1010 -
#800000
b10 +
b1000 *
b0 +
b1000 "
0#
05
04
03
12
06
0$
1(
1%
09
0&
07
1&
08
1$
0(
0%
#810000
b1 +
1#
16
1'
#811000
b1011 -
#820000
b10 +
b1001 *
b0 +
b1001 "
0#
15
06
#830000
b1 +
1#
16
0'
17
0&
18
1%
#831000
b1100 -
#840000
b10 +
b1010 *
b0 +
b1010 "
0#
05
14
06
1&
07
0&
#850000
b1 +
1#
16
1'
#851000
b1101 -
#860000
b10 +
b1011 *
b0 +
b1011 "
0#
15
06
#870000
b1 +
1#
16
0'
17
1&
#871000
b1110 -
#880000
b10 +
b1100 *
b0 +
b1100 "
0#
05
04
13
06
0%
19
0&
07
1&
08
0$
1(
1%
09
1$
0(
#890000
b1 +
1#
16
1'
#891000
b1111 -
#900000
b10 +
b1101 *
b0 +
b1101 "
0#
15
06
#910000
b1 +
1#
16
0'
17
0&
18
0%
19
0$
1(
#911000
b10000 -
#920000
b10 +
b1110 *
b0 +
b1110 "
0#
05
14
06
1&
07
0&
#930000
b1 +
1#
16
1'
#931000
b10001 -
#940000
b10 +
b1111 *
b0 +
b1111 "
0#
15
06
#950000
b1 +
1#
16
0'
17
1&
#951000
b10010 -
#960000
b10 +
b10000 *
b11 )
b0 *
b0 +
b11 !
b0 "
0#
05
04
03
02
11
06
1$
0(
1%
09
0&
1'
07
1&
08
0$
0%
#961000
b11 -
#970000
b1 +
1#
16
0'
17
0&
18
1%
#971000
b100 -
#980000
b10 +
b1 *
b0 +
b1 "
0#
15
06
#990000
b1 +
1#
16
1'
#991000
b101 -
#1000000
b10 +
b10 *
b0 +
b10 "
0#
05
14
06
07
#1010000
b1 +
1#
16
0'
17
1&
#1011000
b110 -
#1020000
b10 +
b11 *
b0 +
b11 "
0#
15
06
#1030000
b1 +
1#
16
1'
#1031000
b111 -
#1040000
b10 +
b100 *
b0 +
b100 "
0#
05
04
13
06
07
0%
19
1$
08
1%
09
0$
#1050000
b1 +
1#
16
0'
17
0&
18
0%
19
1$
#1051000
b1000 -
#1060000
b10 +
b101 *
b0 +
b101 "
0#
15
06
#1070000
b1 +
1#
16
1'
#1071000
b1001 -
#1080000
b10 +
b110 *
b0 +
b110 "
0#
05
14
06
07
#1090000
b1 +
1#
16
0'
17
1&
#1091000
b1010 -
#1100000
b10 +
b111 *
b0 +
b111 "
0#
15
06
#1110000
b1 +
1#
16
1'
#1111000
b1011 -
#1120000
b10 +
b1000 *
b0 +
b1000 "
0#
05
04
03
12
06
07
0$
1(
1%
09
1$
0(
08
0%
#1130000
b1 +
1#
16
0'
17
0&
18
1%
#1131000
b1100 -
#1140000
b10 +
b1001 *
b0 +
b1001 "
0#
15
06
#1150000
b1 +
1#
16
1'
#1151000
b1101 -
#1160000
b10 +
b1010 *
b0 +
b1010 "
0#
05
14
06
07
#1170000
b1 +
1#
16
0'
17
1&
#1171000
b1110 -
#1180000
b10 +
b1011 *
b0 +
b1011 "
0#
15
06
#1190000
b1 +
1#
16
1'
#1191000
b1111 -
#1200000
b10 +
b1100 *
b0 +
b1100 "
0#
05
04
13
06
07
0%
19
0$
1(
08
1%
09
1$
0(
#1210000
b1 +
1#
16
0'
17
0&
18
0%
19
0$
1(
#1211000
b10000 -
#1220000
b10 +
b1101 *
b0 +
b1101 "
0#
15
06
#1230000
b1 +
1#
16
1'
#1231000
b10001 -
#1240000
b10 +
b1110 *
b0 +
b1110 "
0#
05
14
06
07
#1250000
b1 +
1#
16
0'
17
1&
#1251000
b10010 -
#1260000
b10 +
b1111 *
b0 +
b1111 "
0#
15
06
#1270000
b1 +
1#
16
1'
#1271000
b10011 -
#1280000
b10 +
b10000 *
b100 )
b0 *
b0 +
b100 !
b0 "
0#
05
04
03
02
01
00
1/
06
08
07
1$
0(
1%
09
0&
0'
0$
#1281000
b100 -
#1290000
b1 +
1#
16
1'
#1291000
b101 -
#1300000
b10 +
b1 *
b0 +
b1 "
0#
15
06
#1310000
b1 +
1#
16
0'
17
1&
#1311000
b110 -
#1320000
b10 +
b10 *
b0 +
b10 "
0#
05
14
06
0&
18
07
1&
08
#1330000
b1 +
1#
16
1'
#1331000
b111 -
#1340000
b10 +
b11 *
b0 +
b11 "
0#
15
06
#1350000
b1 +
1#
16
0'
17
0&
18
0%
19
1$
#1351000
b1000 -
#1360000
b10 +
b100 *
b0 +
b100 "
0#
05
04
13
06
1%
1&
08
07
0&
0%
#1370000
b1 +
1#
16
1'
#1371000
b1001 -
#1380000
b10 +
b101 *
b0 +
b101 "
0#
15
06
#1390000
b1 +
1#
16
0'
17
1&
#1391000
b1010 -
#1400000
b10 +
b110 *
b0 +
b110 "
0#
05
14
06
0&
18
07
1&
08
#1410000
b1 +
1#
16
1'
#1411000
b1011 -
#1420000
b10 +
b111 *
b0 +
b111 "
0#
15
06
#1430000
b1 +
1#
16
0'
17
0&
18
1%
#1431000
b1100 -
#1440000
b10 +
b1000 *
b0 +
b1000 "
0#
05
04
03
12
06
0$
1(
0%
1&
08
07
0&
1%
09
1$
0(
#1450000
b1 +
1#
16
1'
#1451000
b1101 -
#1460000
b10 +
b1001 *
b0 +
b1001 "
0#
15
06
#1470000
b1 +
1#
16
0'
17
1&
#1471000
b1110 -
#1480000
b10 +
b1010 *
b0 +
b1010 "
0#
05
14
06
0&
18
07
1&
08
#1490000
b1 +
1#
16
1'
#1491000
b1111 -
#1500000
b10 +
b1011 *
b0 +
b1011 "
0#
15
06
#1510000
b1 +
1#
16
0'
17
0&
18
0%
19
0$
1(
#1511000
b10000 -
#1520000
b10 +
b1100 *
b0 +
b1100 "
0#
05
04
13
06
1%
1&
08
07
0&
0%
#1530000
b1 +
1#
16
1'
#1531000
b10001 -
#1540000
b10 +
b1101 *
b0 +
b1101 "
0#
15
06
#1550000
b1 +
1#
16
0'
17
1&
#1551000
b10010 -
#1560000
b10 +
b1110 *
b0 +
b1110 "
0#
05
14
06
0&
18
07
1&
08
#1570000
b1 +
1#
16
1'
#1571000
b10011 -
#1580000
b10 +
b1111 *
b0 +
b1111 "
0#
15
06
#1590000
b1 +
1#
16
0'
17
0&
18
1%
#1591000
b10100 -
#1600000
b10 +
b10000 *
b101 )
b0 *
b0 +
b101 !
b0 "
0#
05
04
03
02
11
06
1$
0(
0%
1&
08
1'
07
0&
1%
09
0$
#1601000
b101 -
#1610000
b1 +
1#
16
0'
17
1&
#1611000
b110 -
#1620000
b10 +
b1 *
b0 +
b1 "
0#
15
06
#1630000
b1 +
1#
16
1'
#1631000
b111 -
#1640000
b10 +
b10 *
b0 +
b10 "
0#
05
14
06
07
#1650000
b1 +
1#
16
0'
17
0&
18
0%
19
1$
#1651000
b1000 -
#1660000
b10 +
b11 *
b0 +
b11 "
0#
15
06
#1670000
b1 +
1#
16
1'
#1671000
b1001 -
#1680000
b10 +
b100 *
b0 +
b100 "
0#
05
04
13
06
07
1%
08
0%
#1690000
b1 +
1#
16
0'
17
1&
#1691000
b1010 -
#1700000
b10 +
b101 *
b0 +
b101 "
0#
15
06
#1710000
b1 +
1#
16
1'
#1711000
b1011 -
#1720000
b10 +
b110 *
b0 +
b110 "
0#
05
14
06
07
#1730000
b1 +
1#
16
0'
17
0&
18
1%
#1731000
b1100 -
#1740000
b10 +
b111 *
b0 +
b111 "
0#
15
06
#1750000
b1 +
1#
16
1'
#1751000
b1101 -
#1760000
b10 +
b1000 *
b0 +
b1000 "
0#
05
04
03
12
06
07
0$
1(
0%
08
1%
09
1$
0(
#1770000
b1 +
1#
16
0'
17
1&
#1771000
b1110 -
#1780000
b10 +
b1001 *
b0 +
b1001 "
0#
15
06
#1790000
b1 +
1#
16
1'
#1791000
b1111 -
#1800000
b10 +
b1010 *
b0 +
b1010 "
0#
05
14
06
07
#1810000
b1 +
1#
16
0'
17
0&
18
0%
19
0$
1(
#1811000
b10000 -
#1820000
b10 +
b1011 *
b0 +
b1011 "
0#
15
06
#1830000
b1 +
1#
16
1'
#1831000
b10001 -
#1840000
b10 +
b1100 *
b0 +
b1100 "
0#
05
04
13
06
07
1%
08
0%
#1850000
b1 +
1#
16
0'
17
1&
#1851000
b10010 -
#1860000
b10 +
b1101 *
b0 +
b1101 "
0#
15
06
#1870000
b1 +
1#
16
1'
#1871000
b10011 -
#1880000
b10 +
b1110 *
b0 +
b1110 "
0#
05
14
06
07
#1890000
b1 +
1#
16
0'
17
0&
18
1%
#1891000
b10100 -
#1900000
b10 +
b1111 *
b0 +
b1111 "
0#
15
06
#1910000
b1 +
1#
16
1'
#1911000
b10101 -
#1920000
b10 +
b10000 *
b110 )
b0 *
b0 +
b110 !
b0 "
0#
05
04
03
02
01
10
06
07
1$
0(
0%
1&
08
0'
1%
09
0$
#1921000
b110 -
#1930000
b1 +
1#
16
1'
#1931000
b111 -
#1940000
b10 +
b1 *
b0 +
b1 "
0#
15
06
#1950000
b1 +
1#
16
0'
17
0&
18
0%
19
1$
#1951000
b1000 -
#1960000
b10 +
b10 *
b0 +
b10 "
0#
05
14
06
1&
07
0&
#1970000
b1 +
1#
16
1'
#1971000
b1001 -
#1980000
b10 +
b11 *
b0 +
b11 "
0#
15
06
#1990000
b1 +
1#
16
0'
17
1&
#1991000
b1010 -
#2000000
b10 +
b100 *
b0 +
b100 "
0#
05
04
13
06
1%
0&
07
1&
08
0%
#2010000
b1 +
1#
16
1'
#2011000
b1011 -
#2020000
b10 +
b101 *
b0 +
b101 "
0#
15
06
#2030000
b1 +
1#
16
0'
17
0&
18
1%
#2031000
b1100 -
#2040000
b10 +
b110 *
b0 +
b110 "
0#
05
14
06
1&
07
0&
#2050000
b1 +
1#
16
1'
#2051000
b1101 -
#2060000
b10 +
b111 *
b0 +
b111 "
0#
15
06
#2070000
b1 +
1#
16
0'
17
1&
#2071000
b1110 -
#2080000
b10 +
b1000 *
b0 +
b1000 "
0#
05
04
03
12
06
0$
1(
0%
0&
07
1&
08
1%
09
1$
0(
#2090000
b1 +
1#
16
1'
#2091000
b1111 -
#2100000
b10 +
b1001 *
b0 +
b1001 "
0#
15
06
#2110000
b1 +
1#
16
0'
17
0&
18
0%
19
0$
1(
#2111000
b10000 -
#2120000
b10 +
b1010 *
b0 +
b1010 "
0#
05
14
06
1&
07
0&
#2130000
b1 +
1#
16
1'
#2131000
b10001 -
#2140000
b10 +
b1011 *
b0 +
b1011 "
0#
15
06
#2150000
b1 +
1#
16
0'
17
1&
#2151000
b10010 -
#2160000
b10 +
b1100 *
b0 +
b1100 "
0#
05
04
13
06
1%
0&
07
1&
08
0%
#2170000
b1 +
1#
16
1'
#2171000
b10011 -
#2180000
b10 +
b1101 *
b0 +
b1101 "
0#
15
06
#2190000
b1 +
1#
16
0'
17
0&
18
1%
#2191000
b10100 -
#2200000
b10 +
b1110 *
b0 +
b1110 "
0#
05
14
06
1&
07
0&
#2210000
b1 +
1#
16
1'
#2211000
b10101 -
#2220000
b10 +
b1111 *
b0 +
b1111 "
0#
15
06
#2230000
b1 +
1#
16
0'
17
1&
#2231000
b10110 -
#2240000
b10 +
b10000 *
b111 )
b0 *
b0 +
b111 !
b0 "
0#
05
04
03
02
11
06
1$
0(
0%
0&
1'
07
1&
08
1%
09
0$
#2241000
b111 -
#2250000
b1 +
1#
16
0'
17
0&
18
0%
19
1$
#2251000
b1000 -
#2260000
b10 +
b1 *
b0 +
b1 "
0#
15
06
#2270000
b1 +
1#
16
1'
#2271000
b1001 -
#2280000
b10 +
b10 *
b0 +
b10 "
0#
05
14
06
07
#2290000
b1 +
1#
16
0'
17
1&
#2291000
b1010 -
#2300000
b10 +
b11 *
b0 +
b11 "
0#
15
06
#2310000
b1 +
1#
16
1'
#2311000
b1011 -
#2320000
b10 +
b100 *
b0 +
b100 "
0#
05
04
13
06
07
1%
08
0%
#2330000
b1 +
1#
16
0'
17
0&
18
1%
#2331000
b1100 -
#2340000
b10 +
b101 *
b0 +
b101 "
0#
15
06
#2350000
b1 +
1#
16
1'
#2351000
b1101 -
#2360000
b10 +
b110 *
b0 +
b110 "
0#
05
14
06
07
#2370000
b1 +
1#
16
0'
17
1&
#2371000
b1110 -
#2380000
b10 +
b111 *
b0 +
b111 "
0#
15
06
#2390000
b1 +
1#
16
1'
#2391000
b1111 -
#2400000
b10 +
b1000 *
b0 +
b1000 "
0#
05
04
03
12
06
07
0$
1(
0%
08
1%
09
1$
0(
#2410000
b1 +
1#
16
0'
17
0&
18
0%
19
0$
1(
#2411000
b10000 -
#2420000
b10 +
b1001 *
b0 +
b1001 "
0#
15
06
#2430000
b1 +
1#
16
1'
#2431000
b10001 -
#2440000
b10 +
b1010 *
b0 +
b1010 "
0#
05
14
06
07
#2450000
b1 +
1#
16
0'
17
1&
#2451000
b10010 -
#2460000
b10 +
b1011 *
b0 +
b1011 "
0#
15
06
#2470000
b1 +
1#
16
1'
#2471000
b10011 -
#2480000
b10 +
b1100 *
b0 +
b1100 "
0#
05
04
13
06
07
1%
08
0%
#2490000
b1 +
1#
16
0'
17
0&
18
1%
#2491000
b10100 -
#2500000
b10 +
b1101 *
b0 +
b1101 "
0#
15
06
#2510000
b1 +
1#
16
1'
#2511000
b10101 -
#2520000
b10 +
b1110 *
b0 +
b1110 "
0#
05
14
06
07
#2530000
b1 +
1#
16
0'
17
1&
#2531000
b10110 -
#2540000
b10 +
b1111 *
b0 +
b1111 "
0#
15
06
#2550000
b1 +
1#
16
1'
#2551000
b10111 -
#2560000
b10 +
b10000 *
b1000 )
b0 *
b0 +
b1000 !
b0 "
0#
05
04
03
02
01
00
0/
1.
06
09
08
07
1$
0(
0%
0&
0'
#2561000
b1000 -
#2570000
b1 +
1#
16
1'
#2571000
b1001 -
#2580000
b10 +
b1 *
b0 +
b1 "
0#
15
06
#2590000
b1 +
1#
16
0'
17
1&
#2591000
b1010 -
#2600000
b10 +
b10 *
b0 +
b10 "
0#
05
14
06
0&
18
07
1&
08
#2610000
b1 +
1#
16
1'
#2611000
b1011 -
#2620000
b10 +
b11 *
b0 +
b11 "
0#
15
06
#2630000
b1 +
1#
16
0'
17
0&
18
1%
#2631000
b1100 -
#2640000
b10 +
b100 *
b0 +
b100 "
0#
05
04
13
06
0%
19
1&
08
07
0&
1%
09
#2650000
b1 +
1#
16
1'
#2651000
b1101 -
#2660000
b10 +
b101 *
b0 +
b101 "
0#
15
06
#2670000
b1 +
1#
16
0'
17
1&
#2671000
b1110 -
#2680000
b10 +
b110 *
b0 +
b110 "
0#
05
14
06
0&
18
07
1&
08
#2690000
b1 +
1#
16
1'
#2691000
b1111 -
#2700000
b10 +
b111 *
b0 +
b111 "
0#
15
06
#2710000
b1 +
1#
16
0'
17
0&
18
0%
19
0$
1(
#2711000
b10000 -
#2720000
b10 +
b1000 *
b0 +
b1000 "
0#
05
04
03
12
06
1$
1%
09
1&
08
07
0&
0%
0$
#2730000
b1 +
1#
16
1'
#2731000
b10001 -
#2740000
b10 +
b1001 *
b0 +
b1001 "
0#
15
06
#2750000
b1 +
1#
16
0'
17
1&
#2751000
b10010 -
#2760000
b10 +
b1010 *
b0 +
b1010 "
0#
05
14
06
0&
18
07
1&
08
#2770000
b1 +
1#
16
1'
#2771000
b10011 -
#2780000
b10 +
b1011 *
b0 +
b1011 "
0#
15
06
#2790000
b1 +
1#
16
0'
17
0&
18
1%
#2791000
b10100 -
#2800000
b10 +
b1100 *
b0 +
b1100 "
0#
05
04
13
06
0%
19
1&
08
07
0&
1%
09
#2810000
b1 +
1#
16
1'
#2811000
b10101 -
#2820000
b10 +
b1101 *
b0 +
b1101 "
0#
15
06
#2830000
b1 +
1#
16
0'
17
1&
#2831000
b10110 -
#2840000
b10 +
b1110 *
b0 +
b1110 "
0#
05
14
06
0&
18
07
1&
08
#2850000
b1 +
1#
16
1'
#2851000
b10111 -
#2860000
b10 +
b1111 *
b0 +
b1111 "
0#
15
06
#2870000
b1 +
1#
16
0'
17
0&
18
0%
19
1$
#2871000
b11000 -
#2880000
b10 +
b10000 *
b1001 )
b0 *
b0 +
b1001 !
b0 "
0#
05
04
03
02
11
06
0$
1%
09
1&
08
1'
07
0&
0%
1$
0(
#2881000
b1001 -
#2890000
b1 +
1#
16
0'
17
1&
#2891000
b1010 -
#2900000
b10 +
b1 *
b0 +
b1 "
0#
15
06
#2910000
b1 +
1#
16
1'
#2911000
b1011 -
#2920000
b10 +
b10 *
b0 +
b10 "
0#
05
14
06
07
#2930000
b1 +
1#
16
0'
17
0&
18
1%
#2931000
b1100 -
#2940000
b10 +
b11 *
b0 +
b11 "
0#
15
06
#2950000
b1 +
1#
16
1'
#2951000
b1101 -
#2960000
b10 +
b100 *
b0 +
b100 "
0#
05
04
13
06
07
0%
19
08
1%
09
#2970000
b1 +
1#
16
0'
17
1&
#2971000
b1110 -
#2980000
b10 +
b101 *
b0 +
b101 "
0#
15
06
#2990000
b1 +
1#
16
1'
#2991000
b1111 -
#3000000
b10 +
b110 *
b0 +
b110 "
0#
05
14
06
07
#3010000
b1 +
1#
16
0'
17
0&
18
0%
19
0$
1(
#3011000
b10000 -
#3020000
b10 +
b111 *
b0 +
b111 "
0#
15
06
#3030000
b1 +
1#
16
1'
#3031000
b10001 -
#3040000
b10 +
b1000 *
b0 +
b1000 "
0#
05
04
03
12
06
07
1$
1%
09
08
0%
0$
#3050000
b1 +
1#
16
0'
17
1&
#3051000
b10010 -
#3060000
b10 +
b1001 *
b0 +
b1001 "
0#
15
06
#3070000
b1 +
1#
16
1'
#3071000
b10011 -
#3080000
b10 +
b1010 *
b0 +
b1010 "
0#
05
14
06
07
#3090000
b1 +
1#
16
0'
17
0&
18
1%
#3091000
b10100 -
#3100000
b10 +
b1011 *
b0 +
b1011 "
0#
15
06
#3110000
b1 +
1#
16
1'
#3111000
b10101 -
#3120000
b10 +
b1100 *
b0 +
b1100 "
0#
05
04
13
06
07
0%
19
08
1%
09
#3130000
b1 +
1#
16
0'
17
1&
#3131000
b10110 -
#3140000
b10 +
b1101 *
b0 +
b1101 "
0#
15
06
#3150000
b1 +
1#
16
1'
#3151000
b10111 -
#3160000
b10 +
b1110 *
b0 +
b1110 "
0#
05
14
06
07
#3170000
b1 +
1#
16
0'
17
0&
18
0%
19
1$
#3171000
b11000 -
#3180000
b10 +
b1111 *
b0 +
b1111 "
0#
15
06
#3190000
b1 +
1#
16
1'
#3191000
b11001 -
#3200000
b10 +
b10000 *
b1010 )
b0 *
b0 +
b1010 !
b0 "
0#
05
04
03
02
01
10
06
07
0$
1%
09
1&
08
0'
0%
1$
0(
#3201000
b1010 -
#3210000
b1 +
1#
16
1'
#3211000
b1011 -
#3220000
b10 +
b1 *
b0 +
b1 "
0#
15
06
#3230000
b1 +
1#
16
0'
17
0&
18
1%
#3231000
b1100 -
#3240000
b10 +
b10 *
b0 +
b10 "
0#
05
14
06
1&
07
0&
#3250000
b1 +
1#
16
1'
#3251000
b1101 -
#3260000
b10 +
b11 *
b0 +
b11 "
0#
15
06
#3270000
b1 +
1#
16
0'
17
1&
#3271000
b1110 -
#3280000
b10 +
b100 *
b0 +
b100 "
0#
05
04
13
06
0%
19
0&
07
1&
08
0$
1(
1%
09
1$
0(
#3290000
b1 +
1#
16
1'
#3291000
b1111 -
#3300000
b10 +
b101 *
b0 +
b101 "
0#
15
06
#3310000
b1 +
1#
16
0'
17
0&
18
0%
19
0$
1(
#3311000
b10000 -
#3320000
b10 +
b110 *
b0 +
b110 "
0#
05
14
06
1&
07
0&
#3330000
b1 +
1#
16
1'
#3331000
b10001 -
#3340000
b10 +
b111 *
b0 +
b111 "
0#
15
06
#3350000
b1 +
1#
16
0'
17
1&
#3351000
b10010 -
#3360000
b10 +
b1000 *
b0 +
b1000 "
0#
05
04
03
12
06
1$
1%
09
0&
07
1&
08
0$
0%
#3370000
b1 +
1#
16
1'
#3371000
b10011 -
